README.md
setup.py
MatchFinder/__init__.py
MatchFinder.egg-info/PKG-INFO
MatchFinder.egg-info/SOURCES.txt
MatchFinder.egg-info/dependency_links.txt
MatchFinder.egg-info/top_level.txt
MatchFinder/_internal/__init__.py
MatchFinder/_internal/core.py
MatchFinder/helpers/__init__.py
MatchFinder/helpers/calculations.py
MatchFinder/helpers/formatters.py