Metadata-Version: 2.1
Name: MatchFinder
Version: 1.0.3
Summary: A Python package for finding similar strings with advanced formatting options.
Home-page: https://github.com/memanja/MatchFinder
Author: Manoj Shetty K
Author-email: shettykmanojmask@gmail.com
License: MIT
Classifier: Programming Language :: Python :: 3
Classifier: License :: OSI Approved :: MIT License
Classifier: Operating System :: OS Independent
Requires-Python: >=3.6
